README.md
setup.py
cowherd/__init__.py
cowherd/constants.py
cowherd/cowherd.py
cowherd/data.yaml
cowherd/engine.py
cowherd/objects.py
cowherd/run_gui.py
cowherd/run_random.py
cowherd/worldgen.py
cowherd.egg-info/PKG-INFO
cowherd.egg-info/SOURCES.txt
cowherd.egg-info/dependency_links.txt
cowherd.egg-info/entry_points.txt
cowherd.egg-info/requires.txt
cowherd.egg-info/top_level.txt
cowherd/assets/1.png
cowherd/assets/2.png
cowherd/assets/3.png
cowherd/assets/4.png
cowherd/assets/5.png
cowherd/assets/arrow-down.png
cowherd/assets/arrow-left.png
cowherd/assets/arrow-right.png
cowherd/assets/arrow-up.png
cowherd/assets/coal.png
cowherd/assets/cow-molken.png
cowherd/assets/cow.png
cowherd/assets/diamond.png
cowherd/assets/fence.png
cowherd/assets/furnace.png
cowherd/assets/grass.png
cowherd/assets/heart.png
cowherd/assets/infinity.png
cowherd/assets/iron.png
cowherd/assets/iron_pickaxe.png
cowherd/assets/iron_sword.png
cowherd/assets/lava.png
cowherd/assets/leaves.png
cowherd/assets/log.png
cowherd/assets/milk.png
cowherd/assets/path.png
cowherd/assets/player-down.png
cowherd/assets/player-left.png
cowherd/assets/player-right.png
cowherd/assets/player-up.png
cowherd/assets/player.png
cowherd/assets/sand.png
cowherd/assets/skeleton.png
cowherd/assets/stone.png
cowherd/assets/stone_pickaxe.png
cowherd/assets/stone_sword.png
cowherd/assets/table.png
cowherd/assets/tree.png
cowherd/assets/unknown.png
cowherd/assets/water.png
cowherd/assets/wood.png
cowherd/assets/wood_pickaxe.png
cowherd/assets/wood_sword.png
cowherd/assets/zombie.png