Metadata-Version: 2.1
Name: cowherd
Version: 0.3.0
Summary: Partially-observed visual reinforcement learning domain.
Home-page: http://github.com/danijar/cowherd
License: UNKNOWN
Platform: UNKNOWN
Classifier: Intended Audience :: Science/Research
Classifier: License :: OSI Approved :: MIT License
Classifier: Programming Language :: Python :: 3
Classifier: Topic :: Games/Entertainment
Classifier: Topic :: Scientific/Engineering :: Artificial Intelligence
Provides-Extra: gui
